{"cameraMode":{"drawMode":0,"name":"Shaded","section":"Shading Mode"},"sceneLighting":true,"audioPlay":false,"sceneViewState":{"m_AlwaysRefresh":false,"showFog":true,"showSkybox":true,"showFlares":true,"showImageEffects":true,"showParticleSystems":true,"showVisualEffectGraphs":true,"m_FxEnabled":true},"in2DMode":false,"pivot":{"x":247.73565673828126,"y":328.67352294921877,"z":7123.7626953125},"rotation":{"x":0.0014996937243267894,"y":0.9646304845809937,"z":0.005489133298397064,"w":-0.26354435086250307},"size":219.46896362304688,"orthographic":false}